wab/__init__.py
wab/wab.py
wab-0.0.2.dist-info/licenses/LICENSE
wab-0.0.2.dist-info/WHEEL
wab-0.0.2.dist-info/METADATA
wab-0.0.2.dist-info/RECORD
