Metadata-Version: 2.4
Name: wab
Version: 0.0.2
Summary: WAB: WhatsApp Business Messages send.
Author-email: "Aymen MW (AMW)" <aymenmw@proton.me>
License-Expression: MIT
License-File: LICENSE
Project-URL: Home, https://t.me/TastyCode
